file_field_utils/__init__.py
file_field_utils/admin.py
file_field_utils/apps.py
file_field_utils/models.py
file_field_utils/settings.py
file_field_utils/urls.py
file_field_utils/utils.py
file_field_utils/views.py
file_field_utils/db/__init__.py
file_field_utils/db/fields.py
file_field_utils/db/forms.py
file_field_utils/db/widgets.py
file_field_utils/db/utils/__init__.py
file_field_utils/db/utils/backend.py
file_field_utils/static/admin/css/admin_form_overrides.css
file_field_utils/static/css/file_field_utils.css
file_field_utils/static/js/file_field_utils.js
file_field_utils/templates/file_field_utils/base.html
django_file_field_utils-0.1.5.dist-info/LICENSE.md
django_file_field_utils-0.1.5.dist-info/METADATA
django_file_field_utils-0.1.5.dist-info/WHEEL
django_file_field_utils-0.1.5.dist-info/top_level.txt
django_file_field_utils-0.1.5.dist-info/RECORD
