Metadata-Version: 2.1
Name: django-file-field-utils
Version: 0.1.5
Summary: This package is a set of field and widget that improves the images and files field behaviour
Home-page: https://github.com/frankhood/django-file-field-utils
Author: FrankHood Business Solutions srl
Author-email: info@frankhood.it
License: MIT
Keywords: django-file-field-utils
Platform: UNKNOWN
Classifier: Development Status :: 3 - Alpha
Classifier: Framework :: Django :: 2.2
Classifier: Framework :: Django :: 3.2
Classifier: Intended Audience :: Developers
Classifier: License :: OSI Approved :: BSD License
Classifier: Natural Language :: English
Classifier: Programming Language :: Python :: 3.6
Classifier: Programming Language :: Python :: 3.7
Classifier: Programming Language :: Python :: 3.8
Classifier: Programming Language :: Python :: 3.9
License-File: LICENSE.md
Requires-Dist: Django (>=2.2)
Requires-Dist: easy-thumbnails (==2.8)
Requires-Dist: click (==8.0.2)
Requires-Dist: importlib-metadata (==4.8.3)
Requires-Dist: Pillow (==8.4.0)
Requires-Dist: filelock (==3.4.1)
Requires-Dist: flake8 (==2.3.0)
Requires-Dist: keyring (==23.4.1)
Requires-Dist: platformdirs (==2.4.0)
Requires-Dist: rfc3986 (==1.5.0)
Requires-Dist: zipp (==3.6.0)
Requires-Dist: mypy
